DS_start/__init__.py
DS_start/basic_EDA.py
DS_basic_start-0.0.10.dist-info/LICENSE
DS_basic_start-0.0.10.dist-info/METADATA
DS_basic_start-0.0.10.dist-info/WHEEL
DS_basic_start-0.0.10.dist-info/top_level.txt
DS_basic_start-0.0.10.dist-info/RECORD
